moncash/__init__.py
moncash/configuration.py
moncash/constants.py
moncash/environment.py
moncash/gateway.py
moncash/http.py
moncash/payement.py
moncash/version.py
moncash/exceptions/__init__.py
moncash/exceptions/authentication_error.py
moncash/exceptions/authorization_error.py
moncash/exceptions/configuration_error.py
moncash/exceptions/environment_error.py
moncash/exceptions/gateway_timeout_error.py
moncash/exceptions/moncash_error.py
moncash/exceptions/not_found_error.py
moncash/exceptions/payment_error.py
moncash/exceptions/request_timeout_error.py
moncash/exceptions/server_error.py
moncash/exceptions/service_unavailable_error.py
moncash/exceptions/too_many_requests_error.py
moncash/exceptions/unexpected_error.py
moncash/exceptions/upgrade_required_error.py
moncash/exceptions/http/__init__.py
moncash/exceptions/http/connection_error.py
moncash/exceptions/http/invalid_response_error.py
moncash/exceptions/http/timeout_error.py
moncash-1.0.2.dist-info/LICENSE
moncash-1.0.2.dist-info/METADATA
moncash-1.0.2.dist-info/WHEEL
moncash-1.0.2.dist-info/top_level.txt
moncash-1.0.2.dist-info/RECORD
