Metadata-Version: 2.1
Name: moncash
Version: 1.0.2
Summary: Moncash Python SDK
Home-page: https://github.com/dokla/moncash_python
Author: Madsen Servius
Author-email: madsen@dokla.ht
License: MIT
Platform: UNKNOWN
Classifier: License :: OSI Approved :: MIT License
Classifier: Programming Language :: Python :: 3.5
Classifier: Programming Language :: Python :: 3.6
Classifier: Programming Language :: Python :: 3.7
Classifier: Programming Language :: Python :: 3.8
Requires-Dist: requests (<3.0,>=2.25.1)
